Workbook

Sheet Ringkasan
A1: Pain Mining: Tilam (Malaysia)
A2: Sumber: forum Lowyat, thread 'Household Mattress, which brand to go for?' (2017–2025). Kiraan di bawah dikira terus dari tab 'Ayat Pain'.
A4: Jumlah ayat pain | B4: =COUNTA('Ayat Pain'!E2:E59) -> 58
A6: Kategori pain | B6: Bil. ayat | C6: % daripada jumlah | D6: Contoh ayat paling kuat
A7: Terlalu lembut / keras | B7: =COUNTIF('Ayat Pain'!$D$2:$D$59,A7) -> 11 | C7: =IF($B$4=0,0,B7/$B$4) -> 0.18965517 | D7: I did. I guess everyone's definition of firm/hard is different.
A8: Harga / takut rugi | B8: =COUNTIF('Ayat Pain'!$D$2:$D$59,A8) -> 9 | C8: =IF($B$4=0,0,B8/$B$4) -> 0.15517241 | D8: And is there really significant differences in quality between price bracket of 3-5k mattress vs 8-10k mattress?
A9: Maklumat produk kurang / keliru memilih | B9: =COUNTIF('Ayat Pain'!$D$2:$D$59,A9) -> 7 | C9: =IF($B$4=0,0,B9/$B$4) -> 0.12068966 | D9: Too many mattress in market dunno which one suppose to test/buy...
A10: Sakit belakang / badan | B10: =COUNTIF('Ayat Pain'!$D$2:$D$59,A10) -> 6 | C10: =IF($B$4=0,0,B10/$B$4) -> 0.10344828 | D10: After less than 1 month, i started having back issues.
A11: Jurujual / harga tak telus | B11: =COUNTIF('Ayat Pain'!$D$2:$D$59,A11) -> 6 | C11: =IF($B$4=0,0,B11/$B$4) -> 0.10344828 | D11: A quick shop around reveal the price is actually RM1.2k (the initial shop try to chop chop me).
A12: Waranti mengelirukan | B12: =COUNTIF('Ayat Pain'!$D$2:$D$59,A12) -> 4 | C12: =IF($B$4=0,0,B12/$B$4) -> 0.068965517 | D12: re-sellers claim 10 yr warranty means 1-to-1 replacement, but Getha themselves say they'll repair it (typically by putting in more foam)
A13: Mendap / lekuk | B13: =COUNTIF('Ayat Pain'!$D$2:$D$59,A13) -> 3 | C13: =IF($B$4=0,0,B13/$B$4) -> 0.051724138 | D13: How do they feel after 6 months / 1year of usage? Still firm or dented already?
A14: Kualiti / ketahanan | B14: =COUNTIF('Ayat Pain'!$D$2:$D$59,A14) -> 3 | C14: =IF($B$4=0,0,B14/$B$4) -> 0.051724138 | D14: I touch the side of the mattress, it looks so cheap that can I touch the spring directly.
A15: Kotor / kebersihan | B15: =COUNTIF('Ayat Pain'!$D$2:$D$59,A15) -> 2 | C15: =IF($B$4=0,0,B15/$B$4) -> 0.034482759 | D15: i only sit on the display bed so far (i afraid too many ppl lay down have virus on bed)
A16: Pilihan / akses terhad | B16: =COUNTIF('Ayat Pain'!$D$2:$D$59,A16) -> 2 | C16: =IF($B$4=0,0,B16/$B$4) -> 0.034482759 | D16: Hard to find mattress shop here
A17: Penghantaran / angkut | B17: =COUNTIF('Ayat Pain'!$D$2:$D$59,A17) -> 2 | C17: =IF($B$4=0,0,B17/$B$4) -> 0.034482759 | D17: I can only consider mattress in the box due to having low ceiling and narrow staircase at my house.
A18: Panas / tak sejuk | B18: =COUNTIF('Ayat Pain'!$D$2:$D$59,A18) -> 1 | C18: =IF($B$4=0,0,B18/$B$4) -> 0.017241379 | D18: I sleep without the AC, and use a single fan in my room so I'd like something that retains coolness.
... A20: Gangguan pasangan | B20: =COUNTIF('Ayat Pain'!$D$2:$D$59,A20) -> 1 | C20: =IF($B$4=0,0,B20/$B$4) -> 0.017241379 | D20: has low disturbance as I like to toss and turn until I sleep.
A21: Jumlah | B21: =SUM(B7:B20) -> 58
A23: Apa maksudnya: peluang produk / mesej
A24: (Tafsiran Claude daripada data di atas, bukan petikan.)
A25: 1. Orang tak faham 'keras vs firm vs medium' | B25: Kumpulan terbesar. Ramai beli ikut label kekerasan, lepas tu menyesal sebab label setiap jenama lain-lain. Peluang: kuiz/padanan tilam ikut posisi tidur + berat badan, atau jual dengan percubaan tidur di rumah. Topper boleh jadi produk 'pembetul' untuk yang dah tersalah beli.
A26: 2. Takut rugi + tak percaya jurujual | B26: Gabungan harga, jurujual dan waranti ialah tema paling besar kalau dikira bersama. Orang tak pasti beza tilam RM3k vs RM8k, dan rasa harga showroom 'dicekik'. Peluang: harga telus, perbandingan jujur, polisi pulang/refund yang jelas.
A27: 3. Sakit belakang ialah pencetus beli | B27: Ramai mula cari tilam sebab sakit belakang atau pasangan sakit. Mesej 'sokongan tulang belakang' kena, tapi elak janji perubatan.
A28: 4. Waranti & mendap | B28: Syarat waranti (mesti lekuk 1.5 inci, rangka katil 'sesuai', bayar sebahagian kos baiki) buat orang curiga. Peluang: waranti ringkas yang mudah difahami jadi pembeza.
A29: 5. Isu kecil tapi spesifik | B29: Bilik panas tanpa aircond, tangga sempit (tilam dalam kotak), kawasan kecil susah cari kedai, kebersihan tilam display. Sesuai jadi sudut iklan atau kandungan niche.

Sheet Ayat Pain
A1: No | B1: Platform | C1: Tarikh | D1: Kategori | E1: Ayat (verbatim) | F1: Link sumber
A2: 1 | B2: Lowyat | C2: 2020-01-11 | D2: Terlalu lembut / keras | E2: a little bit on the soft side but it's comfy as it has 2 inch latex at the top but not sure if it's good for the spine | F2: https://forum.lowyat.net/topic/843907/+6260
A3: 2 | B3: Lowyat | C3: 2020-02-02 | D3: Terlalu lembut / keras | E3: I did. I guess everyone's definition of firm/hard is different. | F3: https://forum.lowyat.net/topic/843907/+6260
A4: 3 | B4: Lowyat | C4: 2020-02-02 | D4: Terlalu lembut / keras | E4: Now Aerofoam Jade when I sit on it it sinks - isn't that soft...? | F4: https://forum.lowyat.net/topic/843907/+6260
A5: 4 | B5: Lowyat | C5: 2020-09-18 | D5: Terlalu lembut / keras | E5: Anyone can suggest a good mattress that is firm and soft at the same time | F5: https://forum.lowyat.net/topic/843907/+6520
A6: 5 | B6: Lowyat | C6: 2021-12-16 | D6: Terlalu lembut / keras | E6: are those nice hotel mattress suitable for home use? could it be too soft/comfy good for a few days sleep. but for long term might not provide enough support. | F6: https://forum.lowyat.net/topic/843907/+6960
A7: 6 | B7: Lowyat | C7: 2021-12-31 | D7: Terlalu lembut / keras | E7: Wish to have firm mattress (not hard) without sacrificing much on the comfort. | F7: https://forum.lowyat.net/topic/843907/+6960
A8: 7 | B8: Lowyat | C8: 2022-01-01 | D8: Terlalu lembut / keras | E8: VONO AVERY is just nice but somehow feel lack of something. KINGKOIL HOSPITALITY is very firm, erm not preferable. | F8: https://forum.lowyat.net/topic/843907/+6960
A9: 8 | B9: Lowyat | C9: 2023-07-22 | D9: Terlalu lembut / keras | E9: i do not prefer soft one, hard to bangun. even sofa pun tak boleh soft ones. | F9: https://forum.lowyat.net/topic/843907/+7487
A10: 9 | B10: Lowyat | C10: 2025-09-04 | D10: Terlalu lembut / keras | E10: What i need is soft but not that soft until got drowning feeling or saggy feeling and i like high thick mattress too and if it has cooling feature | F10: https://forum.lowyat.net/topic/843907/+7980
A11: 10 | B11: Lowyat | C11: 2025-09-04 | D11: Terlalu lembut / keras | E11: I have used king koil for almost 10 years, overall didnt really like it, feels abit hard | F11: https://forum.lowyat.net/topic/843907/+7980
A12: 11 | B12: Lowyat | C12: 2025-10-13 | D12: Terlalu lembut / keras | E12: I think it is best to try them out before buying because I also tried their Rio series back then which cost more but was kinda too soft for my liking. | F12: https://forum.lowyat.net/topic/843907/+8000
A13: 12 | B13: Lowyat | C13: - | D13: Harga / takut rugi | E13: looks like all mattress price gone up already.. | F13: https://forum.lowyat.net/topic/843907/+440
... A59: 58 | B59: Lowyat | C59: 2025-10-13 | D59: Gangguan pasangan | E59: do you have something firmer than Sealy Posturepedic Elevate Cortland and has low disturbance as I like to toss and turn until I sleep. | F59: https://forum.lowyat.net/topic/843907/+7980

Sheet Nota
A1: Perkara | B1: Nota
A2: Kaedah | B2: Ayat diambil verbatim daripada halaman awam forum Lowyat, thread 'Household Mattress, which brand to go for?'. Satu baris = satu ayat pain. Nama pengguna tidak disimpan.
A3: Liputan | B3: 10 halaman daripada thread itu (2017–2025). Ini sampel, bukan semua 402 halaman.
A4: Tidak termasuk | B4: Reddit: disekat dari sesi ini. Threads & TikTok: perlu browser di komputer awak, yang tak bersambung masa kerja ini dibuat.
A5: Kategori | B5: Dilabel secara manual oleh Claude; satu ayat satu kategori. Boleh tukar di kolum D tab 'Ayat Pain' dan kiraan Ringkasan akan ikut.
A6: Bias | B6: Pengguna Lowyat cenderung lelaki, urban, berbahasa Inggeris dan bajet sederhana-tinggi. Suara pembeli B40/BM kurang diwakili; Threads/TikTok akan imbangkan.
