Workbook

Sheet Ringkasan
A1: Pain Mining: Tilam (Malaysia)
A2: Sumber: Threads, komen TikTok dan forum Lowyat. Semua angka dikira terus daripada tab 'Ayat Pain'.
A4: Jumlah ayat pain | B4: =COUNTA('Ayat Pain'!$F$2:$F$170) -> 169
A5: Threads | B5: =COUNTIF('Ayat Pain'!$B$2:$B$170,"Threads") -> 49
A6: TikTok | B6: =COUNTIF('Ayat Pain'!$B$2:$B$170,"TikTok") -> 62
A7: Lowyat | B7: =COUNTIF('Ayat Pain'!$B$2:$B$170,"Lowyat") -> 58
A8: Sebut Coway | B8: =COUNTIF('Ayat Pain'!$H$2:$H$170,"Ya") -> 38
A10: Kategori pain | B10: Jumlah | C10: % | D10: Threads | E10: TikTok | F10: Lowyat | G10: Coway | H10: Contoh ayat paling kuat
A11: Harga / takut rugi | B11: =COUNTIF('Ayat Pain'!$E$2:$E$170,A11) -> 19 | C11: =IF($B$4=0,0,B11/$B$4) -> 0.11242604 | D11: =COUNTIFS('Ayat Pain'!$E$2:$E$170,$A11,'Ayat Pain'!$B$2:$B$170,"Threads") -> 6 | E11: =COUNTIFS('Ayat Pain'!$E$2:$E$170,$A11,'Ayat Pain'!$B$2:$B$170,"TikTok") -> 4 | F11: =COUNTIFS('Ayat Pain'!$E$2:$E$170,$A11,'Ayat Pain'!$B$2:$B$170,"Lowyat") -> 9 | G11: =COUNTIFS('Ayat Pain'!$E$2:$E$170,$A11,'Ayat Pain'!$H$2:$H$170,"Ya") -> 3 | H11: Terkejutnya aku dengan harga tilam korang beli. HAHAHAH memang harga tilam sampai 2k-5k ke dooooo
A12: Terlalu lembut / keras | B12: =COUNTIF('Ayat Pain'!$E$2:$E$170,A12) -> 19 | C12: =IF($B$4=0,0,B12/$B$4) -> 0.11242604 | D12: =COUNTIFS('Ayat Pain'!$E$2:$E$170,$A12,'Ayat Pain'!$B$2:$B$170,"Threads") -> 2 | E12: =COUNTIFS('Ayat Pain'!$E$2:$E$170,$A12,'Ayat Pain'!$B$2:$B$170,"TikTok") -> 6 | F12: =COUNTIFS('Ayat Pain'!$E$2:$E$170,$A12,'Ayat Pain'!$B$2:$B$170,"Lowyat") -> 11 | G12: =COUNTIFS('Ayat Pain'!$E$2:$E$170,$A12,'Ayat Pain'!$H$2:$H$170,"Ya") -> 3 | H12: sy dh beli tilam dreamland ni, mlm pertama tidur sakit betul badan mcm terlalu keras bagi sy
A13: Sakit belakang / badan | B13: =COUNTIF('Ayat Pain'!$E$2:$E$170,A13) -> 18 | C13: =IF($B$4=0,0,B13/$B$4) -> 0.10650888 | D13: =COUNTIFS('Ayat Pain'!$E$2:$E$170,$A13,'Ayat Pain'!$B$2:$B$170,"Threads") -> 4 | E13: =COUNTIFS('Ayat Pain'!$E$2:$E$170,$A13,'Ayat Pain'!$B$2:$B$170,"TikTok") -> 8 | F13: =COUNTIFS('Ayat Pain'!$E$2:$E$170,$A13,'Ayat Pain'!$B$2:$B$170,"Lowyat") -> 6 | G13: =COUNTIFS('Ayat Pain'!$E$2:$E$170,$A13,'Ayat Pain'!$H$2:$H$170,"Ya") -> 4 | H13: tilam sy skrg punca sy sakit badan, boleh sy tahu suggestion mana yg ssuai? sbb tgh cari tilam, xdaya dh nk tahan badan n sakit blkg
A14: Maklumat produk kurang / keliru memilih | B14: =COUNTIF('Ayat Pain'!$E$2:$E$170,A14) -> 15 | C14: =IF($B$4=0,0,B14/$B$4) -> 0.088757396 | D14: =COUNTIFS('Ayat Pain'!$E$2:$E$170,$A14,'Ayat Pain'!$B$2:$B$170,"Threads") -> 4 | E14: =COUNTIFS('Ayat Pain'!$E$2:$E$170,$A14,'Ayat Pain'!$B$2:$B$170,"TikTok") -> 4 | F14: =COUNTIFS('Ayat Pain'!$E$2:$E$170,$A14,'Ayat Pain'!$B$2:$B$170,"Lowyat") -> 7 | G14: =COUNTIFS('Ayat Pain'!$E$2:$E$170,$A14,'Ayat Pain'!$H$2:$H$170,"Ya") -> 0 | H14: Too many mattress in market dunno which one suppose to test/buy...
A15: Mendap / lekuk | B15: =COUNTIF('Ayat Pain'!$E$2:$E$170,A15) -> 13 | C15: =IF($B$4=0,0,B15/$B$4) -> 0.076923077 | D15: =COUNTIFS('Ayat Pain'!$E$2:$E$170,$A15,'Ayat Pain'!$B$2:$B$170,"Threads") -> 4 | E15: =COUNTIFS('Ayat Pain'!$E$2:$E$170,$A15,'Ayat Pain'!$B$2:$B$170,"TikTok") -> 6 | F15: =COUNTIFS('Ayat Pain'!$E$2:$E$170,$A15,'Ayat Pain'!$B$2:$B$170,"Lowyat") -> 3 | G15: =COUNTIFS('Ayat Pain'!$E$2:$E$170,$A15,'Ayat Pain'!$H$2:$H$170,"Ya") -> 1 | H15: Takut nk beli yg below 500 sbb last time beli guna 4bulan dah melendut tau sakit belakang tidur😭
A16: Kotor / kebersihan | B16: =COUNTIF('Ayat Pain'!$E$2:$E$170,A16) -> 12 | C16: =IF($B$4=0,0,B16/$B$4) -> 0.071005917 | D16: =COUNTIFS('Ayat Pain'!$E$2:$E$170,$A16,'Ayat Pain'!$B$2:$B$170,"Threads") -> 4 | E16: =COUNTIFS('Ayat Pain'!$E$2:$E$170,$A16,'Ayat Pain'!$B$2:$B$170,"TikTok") -> 6 | F16: =COUNTIFS('Ayat Pain'!$E$2:$E$170,$A16,'Ayat Pain'!$B$2:$B$170,"Lowyat") -> 2 | G16: =COUNTIFS('Ayat Pain'!$E$2:$E$170,$A16,'Ayat Pain'!$H$2:$H$170,"Ya") -> 3 | H16: anak saiya terkencing atas tilam while potty train, dah basuh tilam jadi begini pula . Dah pakai alas waterproof tapi mana silapnya, tetap bocor juga.
A17: Jurujual / harga tak telus | B17: =COUNTIF('Ayat Pain'!$E$2:$E$170,A17) -> 12 | C17: =IF($B$4=0,0,B17/$B$4) -> 0.071005917 | D17: =COUNTIFS('Ayat Pain'!$E$2:$E$170,$A17,'Ayat Pain'!$B$2:$B$170,"Threads") -> 1 | E17: =COUNTIFS('Ayat Pain'!$E$2:$E$170,$A17,'Ayat Pain'!$B$2:$B$170,"TikTok") -> 5 | F17: =COUNTIFS('Ayat Pain'!$E$2:$E$170,$A17,'Ayat Pain'!$B$2:$B$170,"Lowyat") -> 6 | G17: =COUNTIFS('Ayat Pain'!$E$2:$E$170,$A17,'Ayat Pain'!$H$2:$H$170,"Ya") -> 5 | H17: Agent prnah wsap husband push amek tilam coway..bila tny brapa per bulan, brapa tahun. Hmm dah block je num agent tu 😅
A18: Kontrak / bayaran bulanan / servis | B18: =COUNTIF('Ayat Pain'!$E$2:$E$170,A18) -> 12 | C18: =IF($B$4=0,0,B18/$B$4) -> 0.071005917 | D18: =COUNTIFS('Ayat Pain'!$E$2:$E$170,$A18,'Ayat Pain'!$B$2:$B$170,"Threads") -> 7 | E18: =COUNTIFS('Ayat Pain'!$E$2:$E$170,$A18,'Ayat Pain'!$B$2:$B$170,"TikTok") -> 5 | F18: =COUNTIFS('Ayat Pain'!$E$2:$E$170,$A18,'Ayat Pain'!$B$2:$B$170,"Lowyat") -> 0 | G18: =COUNTIFS('Ayat Pain'!$E$2:$E$170,$A18,'Ayat Pain'!$H$2:$H$170,"Ya") -> 12 | H18: X berbaloi utk amik monthly installment. Kalau u kira amik bayar lum sum lagi banyak jimat. Jgn terpedaya.
A19: Kualiti / ketahanan | B19: =COUNTIF('Ayat Pain'!$E$2:$E$170,A19) -> 9 | C19: =IF($B$4=0,0,B19/$B$4) -> 0.053254438 | D19: =COUNTIFS('Ayat Pain'!$E$2:$E$170,$A19,'Ayat Pain'!$B$2:$B$170,"Threads") -> 4 | E19: =COUNTIFS('Ayat Pain'!$E$2:$E$170,$A19,'Ayat Pain'!$B$2:$B$170,"TikTok") -> 2 | F19: =COUNTIFS('Ayat Pain'!$E$2:$E$170,$A19,'Ayat Pain'!$B$2:$B$170,"Lowyat") -> 3 | G19: =COUNTIFS('Ayat Pain'!$E$2:$E$170,$A19,'Ayat Pain'!$H$2:$H$170,"Ya") -> 0 | H19: kalau pakai lama sikit spring dia terkeluaq sakit taw kena cucuk.
A20: Penghantaran / angkut / buang | B20: =COUNTIF('Ayat Pain'!$E$2:$E$170,A20) -> 9 | C20: =IF($B$4=0,0,B20/$B$4) -> 0.053254438 | D20: =COUNTIFS('Ayat Pain'!$E$2:$E$170,$A20,'Ayat Pain'!$B$2:$B$170,"Threads") -> 2 | E20: =COUNTIFS('Ayat Pain'!$E$2:$E$170,$A20,'Ayat Pain'!$B$2:$B$170,"TikTok") -> 5 | F20: =COUNTIFS('Ayat Pain'!$E$2:$E$170,$A20,'Ayat Pain'!$B$2:$B$170,"Lowyat") -> 2 | G20: =COUNTIFS('Ayat Pain'!$E$2:$E$170,$A20,'Ayat Pain'!$H$2:$H$170,"Ya") -> 1 | H20: I can only consider mattress in the box due to having low ceiling and narrow staircase at my house.
A21: Tak percaya review / affiliate | B21: =COUNTIF('Ayat Pain'!$E$2:$E$170,A21) -> 9 | C21: =IF($B$4=0,0,B21/$B$4) -> 0.053254438 | D21: =COUNTIFS('Ayat Pain'!$E$2:$E$170,$A21,'Ayat Pain'!$B$2:$B$170,"Threads") -> 6 | E21: =COUNTIFS('Ayat Pain'!$E$2:$E$170,$A21,'Ayat Pain'!$B$2:$B$170,"TikTok") -> 3 | F21: =COUNTIFS('Ayat Pain'!$E$2:$E$170,$A21,'Ayat Pain'!$B$2:$B$170,"Lowyat") -> 0 | G21: =COUNTIFS('Ayat Pain'!$E$2:$E$170,$A21,'Ayat Pain'!$H$2:$H$170,"Ya") -> 1 | H21: Honest feedback please, janganlah review tilam tu best just sebab nak letak link je 😔
A22: Waranti mengelirukan | B22: =COUNTIF('Ayat Pain'!$E$2:$E$170,A22) -> 7 | C22: =IF($B$4=0,0,B22/$B$4) -> 0.041420118 | D22: =COUNTIFS('Ayat Pain'!$E$2:$E$170,$A22,'Ayat Pain'!$B$2:$B$170,"Threads") -> 0 | E22: =COUNTIFS('Ayat Pain'!$E$2:$E$170,$A22,'Ayat Pain'!$B$2:$B$170,"TikTok") -> 3 | F22: =COUNTIFS('Ayat Pain'!$E$2:$E$170,$A22,'Ayat Pain'!$B$2:$B$170,"Lowyat") -> 4 | G22: =COUNTIFS('Ayat Pain'!$E$2:$E$170,$A22,'Ayat Pain'!$H$2:$H$170,"Ya") -> 3 | H22: re-sellers claim 10 yr warranty means 1-to-1 replacement, but Getha themselves say they'll repair it (typically by putting in more foam)
... A26: Pilihan / akses terhad | B26: =COUNTIF('Ayat Pain'!$E$2:$E$170,A26) -> 2 | C26: =IF($B$4=0,0,B26/$B$4) -> 0.01183432 | D26: =COUNTIFS('Ayat Pain'!$E$2:$E$170,$A26,'Ayat Pain'!$B$2:$B$170,"Threads") -> 0 | E26: =COUNTIFS('Ayat Pain'!$E$2:$E$170,$A26,'Ayat Pain'!$B$2:$B$170,"TikTok") -> 0 | F26: =COUNTIFS('Ayat Pain'!$E$2:$E$170,$A26,'Ayat Pain'!$B$2:$B$170,"Lowyat") -> 2 | G26: =COUNTIFS('Ayat Pain'!$E$2:$E$170,$A26,'Ayat Pain'!$H$2:$H$170,"Ya") -> 0 | H26: Hard to find mattress shop here
A27: Jumlah | B27: =SUM(B11:B26) -> 169 | D27: =SUM(D11:D26) -> 49 | E27: =SUM(E11:E26) -> 62 | F27: =SUM(F11:F26) -> 58 | G27: =SUM(G11:G26) -> 38
A29: Apa maksudnya
A30: (Tafsiran Claude daripada data di atas, bukan petikan.)
A31: 1. Orang tak percaya review lagi | B31: Threads penuh dengan 'review jujur please', 'jangan promote kat komen', 'affiliate main jauh2'. Pembeli dah muak dengan affiliate yang tak pernah guna. Kandungan yang menang ialah bukti jujur: pengguna sebenar, pakai lama (1–3 tahun), tunjuk kelemahan juga.
A32: 2. 'Firm' vs 'keras' masih mengelirukan | B32: Kekal antara tema terbesar di ketiga-tiga platform. Ramai sakit badan malam pertama kerana tersalah pilih. Kandungan 'cara pilih kekerasan ikut posisi tidur & berat badan' ada permintaan tinggi.
A33: 3. Takut beli murah, takut beli mahal | B33: Pengalaman tilam murah melendut dalam 4 bulan buat orang takut beli bawah RM500, tapi RM2k–5k mengejutkan. Ruang tengah (nilai jangka panjang, kos per tahun) belum dijelaskan dengan baik.
A34: 4. Masalah praktikal rumah Malaysia | B34: Anak kencing atas tilam, bilik panas tanpa aircond, tilam berat naik tangga/loteng, kos pos ke Sabah, cara buang tilam lama. Sudut iklan yang spesifik dan jarang digunakan jenama.
A35: 5. Khusus Coway | B35: Bantahan utama bukan produk, tapi model sewa: '49x12x7=4,116', 'tak nak hutang', 'jgn terpedaya'. Kedua: harga bulanan tak dinyatakan terus, dan ejen dilihat terlalu push. Ketiga: kualiti servis (topper lambat tukar, servis jarang, segan orang masuk bilik). Yang positif banyak juga, terutama sakit belakang hilang dan senang cuci untuk keluarga beranak kecil.

Sheet Ayat Pain
A1: No | B1: Platform | C1: Jenis | D1: Tarikh | E1: Kategori | F1: Ayat (verbatim) | G1: Link sumber | H1: Sebut Coway
A2: 1 | B2: Threads | C2: Post | D2: 2025-05-31 | E2: Harga / takut rugi | F2: Ada survey brand Dreamland, Joey, Origin, Sonno tapi tuh la harga macam keras sikit 👉🏻👈🏻 🥹 | G2: https://www.threads.com/@_eiryeenathasya/post/DKSjjXwhzFV
A3: 2 | B3: Threads | C3: Post | D3: 2025-10-13 | E3: Harga / takut rugi | F3: Dah la mahal tilam, base tilam pun kena beli ikea jugak. | G3: https://www.threads.com/@farhanaaneesa/post/DPvelJTkodi
A4: 3 | B4: Threads | C4: Post | D4: 2025-10-17 | E4: Harga / takut rugi | F4: Terkejutnya aku dengan harga tilam korang beli. HAHAHAH memang harga tilam sampai 2k-5k ke dooooo | G4: https://www.threads.com/@frhnani.j/post/DP4KrJhgXy9
A5: 4 | B5: Threads | C5: Post | D5: 2026-05-24 | E5: Harga / takut rugi | F5: One day nak save up beli Vono sebab memang suka sangat Vono tapi mahal so for now nak beli yang mampu milik dulu sambil simpan duit untuk Vono. | G5: https://www.threads.com/@syasyamazalan_/post/DYuSzWOkmME
A6: 5 | B6: Threads | C6: Post | D6: 2026-08-14 | E6: Harga / takut rugi | F6: Siapa pakai tilam coway? Berbaloi tak? | G6: https://www.threads.com/@symimo_/post/DcANkLPD3Ys | H6: Ya
A7: 6 | B7: Threads | C7: Post | D7: 2026-09-22 | E7: Harga / takut rugi | F7: Baloi tak beli tilam cuckoo / coway tu? Siapa dah beli? | G7: https://www.threads.com/@syamsul.izzat/post/Ddki4HVnxGQ | H7: Ya
A8: 7 | B8: TikTok | C8: Komen | D8: 2025-06-20 | E8: Harga / takut rugi | F8: apa beza tilam premium dgn harga 4 ribu 5 ribu...harga di kedai perabot lagi murah..nak tnya comparison dia..brg apa coway pakai spec | G8: https://www.tiktok.com/@salam_coway/video/7516809339831684370 | H8: Ya
A9: 8 | B9: TikTok | C9: Komen | D9: 2026-07-17 | E9: Harga / takut rugi | F9: mahalnya dh la sakit x blh nk bekerja harga tilam sngt mahal | G9: https://www.tiktok.com/@vonomalaysia/video/7534988212297682183
A10: 9 | B10: TikTok | C10: Komen | D10: 2026-08-15 | E10: Harga / takut rugi | F10: bang just buat konten tilam apa kami bajet sikit tapi nak keselesaan | G10: https://www.tiktok.com/@kudean.zainalhome/video/7673444572055309576
A11: 10 | B11: TikTok | C11: Komen | D11: 2026-08-18 | E11: Harga / takut rugi | F11: untuk low budget ada tk cadangan ? | G11: https://www.tiktok.com/@kudean.zainalhome/video/7673444572055309576
A12: 11 | B12: Lowyat | C12: Post forum | D12: - | E12: Harga / takut rugi | F12: looks like all mattress price gone up already.. | G12: https://forum.lowyat.net/topic/843907/+440
A13: 12 | B13: Lowyat | C13: Post forum | D13: 2020-01-22 | E13: Harga / takut rugi | F13: I know the budget isnt much but im hoping to get a decently value mattress for my tenants la at least.. | G13: https://forum.lowyat.net/topic/843907/+6260
A14: 13 | B14: Lowyat | C14: Post forum | D14: 2020-08 | E14: Harga / takut rugi | F14: for the established brands, queen size medium soft mattress range 1-1.5k is quite hard to fit in. | G14: https://forum.lowyat.net/topic/843907/+6487
A15: 14 | B15: Lowyat | C15: Post forum | D15: 2020-09-15 | E15: Harga / takut rugi | F15: I tried it and it seems okay however I'm still worried to buy it. | G15: https://forum.lowyat.net/topic/843907/+6520
A16: 15 | B16: Lowyat | C16: Post forum | D16: 2022-01-02 | E16: Harga / takut rugi | F16: anyone knows where to get cheaper Serta and Sealy mattress? | G16: https://forum.lowyat.net/topic/843907/+6960
A17: 16 | B17: Lowyat | C17: Post forum | D17: 2023-07-19 | E17: Harga / takut rugi | F17: Will be a big investment for me, so trying to get the best value and comfort in the long-run. | G17: https://forum.lowyat.net/topic/843907/+7487
A18: 17 | B18: Lowyat | C18: Post forum | D18: 2025-10-12 | E18: Harga / takut rugi | F18: I didn't go for full latex mattress because of price and weight of the mattress. | G18: https://forum.lowyat.net/topic/843907/+7980
A19: 18 | B19: Lowyat | C19: Post forum | D19: 2025-10-27 | E19: Harga / takut rugi | F19: What would be a good economical choice queen mattress for rental property? | G19: https://forum.lowyat.net/topic/843907/+8000
A20: 19 | B20: Lowyat | C20: Post forum | D20: 2025-11-03 | E20: Harga / takut rugi | F20: And is there really significant differences in quality between price bracket of 3-5k mattress vs 8-10k mattress? | G20: https://forum.lowyat.net/topic/843907/+8000
... A22: 21 | B22: Threads | C22: Post | D22: 2026-06-04 | E22: Terlalu lembut / keras | F22: Mana nak cari tilam yang tak keras sangat dan tak lembut sangat? Saya ada scoliosis | G22: https://www.threads.com/@lillyaamzn/post/DZKfor-GNUw
A23: 22 | B23: TikTok | C23: Komen | D23: 2026-03-02 | E23: Terlalu lembut / keras | F23: dah sampai,tapi kenapa sakit badan ekk. macam keras la | G23: https://www.tiktok.com/@_syaifulaiman/video/7599517592411360520 | H23: Ya
A24: 23 | B24: TikTok | C24: Komen | D24: 2026-03-03 | E24: Terlalu lembut / keras | F24: mana paling keras mana satu yg bagus soft n firm apa beza | G24: https://www.tiktok.com/@salam_coway/video/7516809339831684370 | H24: Ya
A25: 24 | B25: TikTok | C25: Komen | D25: 2026-04-22 | E25: Terlalu lembut / keras | F25: prime two series ni tilam dia lembut ke keras ya ? sbb sy xnk tilam lembut sgt . | G25: https://www.tiktok.com/@salam_coway/video/7516809339831684370 | H25: Ya
A26: 25 | B26: TikTok | C26: Komen | D26: 2026-05-01 | E26: Terlalu lembut / keras | F26: sy dh beli tilam dreamland ni, mlm pertama tidur sakit betul badan mcm terlalu keras bagi sy | G26: https://www.tiktok.com/@myeidris/video/7297156857053908232
A27: 26 | B27: TikTok | C27: Komen | D27: 2026-08-15 | E27: Terlalu lembut / keras | F27: sy suka tidur mengiring.bangun pg badan selalu sakit sbb tilam keras. | G27: https://www.tiktok.com/@vonomalaysia/video/7527122276873981185
A28: 27 | B28: TikTok | C28: Komen | D28: 2026-09-25 | E28: Terlalu lembut / keras | F28: tilam lembut sakit pinggang, keras better | G28: https://www.tiktok.com/@me_alisya/video/7594685728978701576
A29: 28 | B29: Lowyat | C29: Post forum | D29: 2020-01-11 | E29: Terlalu lembut / keras | F29: a little bit on the soft side but it's comfy as it has 2 inch latex at the top but not sure if it's good for the spine | G29: https://forum.lowyat.net/topic/843907/+6260
A30: 29 | B30: Lowyat | C30: Post forum | D30: 2020-02-02 | E30: Terlalu lembut / keras | F30: I did. I guess everyone's definition of firm/hard is different. | G30: https://forum.lowyat.net/topic/843907/+6260
A31: 30 | B31: Lowyat | C31: Post forum | D31: 2020-02-02 | E31: Terlalu lembut / keras | F31: Now Aerofoam Jade when I sit on it it sinks - isn't that soft...? | G31: https://forum.lowyat.net/topic/843907/+6260
A32: 31 | B32: Lowyat | C32: Post forum | D32: 2020-09-18 | E32: Terlalu lembut / keras | F32: Anyone can suggest a good mattress that is firm and soft at the same time | G32: https://forum.lowyat.net/topic/843907/+6520
A33: 32 | B33: Lowyat | C33: Post forum | D33: 2021-12-16 | E33: Terlalu lembut / keras | F33: are those nice hotel mattress suitable for home use? could it be too soft/comfy good for a few days sleep. but for long term might not provide enough support. | G33: https://forum.lowyat.net/topic/843907/+6960
A34: 33 | B34: Lowyat | C34: Post forum | D34: 2021-12-31 | E34: Terlalu lembut / keras | F34: Wish to have firm mattress (not hard) without sacrificing much on the comfort. | G34: https://forum.lowyat.net/topic/843907/+6960
A35: 34 | B35: Lowyat | C35: Post forum | D35: 2022-01-01 | E35: Terlalu lembut / keras | F35: VONO AVERY is just nice but somehow feel lack of something. KINGKOIL HOSPITALITY is very firm, erm not preferable. | G35: https://forum.lowyat.net/topic/843907/+6960
A36: 35 | B36: Lowyat | C36: Post forum | D36: 2023-07-22 | E36: Terlalu lembut / keras | F36: i do not prefer soft one, hard to bangun. even sofa pun tak boleh soft ones. | G36: https://forum.lowyat.net/topic/843907/+7487
A37: 36 | B37: Lowyat | C37: Post forum | D37: 2025-09-04 | E37: Terlalu lembut / keras | F37: What i need is soft but not that soft until got drowning feeling or saggy feeling and i like high thick mattress too and if it has cooling feature | G37: https://forum.lowyat.net/topic/843907/+7980
... A40: 39 | B40: Threads | C40: Post | D40: 2025-02-25 | E40: Sakit belakang / badan | F40: Sakit belakang. Working long hour. Selalu travel. Bila habis outstation. Rasa barai gila. Susah nak tidur sbb tilam tak selesa. | G40: https://www.threads.com/@nizamtalks/post/DGgGCefPRZT
A41: 40 | B41: Threads | C41: Post | D41: 2026-06-09 | E41: Sakit belakang / badan | F41: Wei tilam coway ni mmg buat sakit tulang belkng ke kalau tido . Ahh stresss | G41: https://www.threads.com/@milieeeeeyy/post/DZWGrv0kyUP | H41: Ya
A42: 41 | B42: Threads | C42: Balasan | D42: 2026-06-09 | E42: Sakit belakang / badan | F42: Tapi btol weh sakit pinggang tauu ..i dengan husb pun sama .. | G42: https://www.threads.com/@miramazlan___/post/DZW368IEsC- | H42: Ya
A43: 42 | B43: Threads | C43: Post | D43: 2026-09-07 | E43: Sakit belakang / badan | F43: Korang...tolong spill brand tilam untuk sakit belakang. Harga mampu milik , tahan lama. Bila umur dh nk masuk 40 an ni , sakit belakang dah mula singgah. | G43: https://www.threads.com/@me_kinna/post/Dc96YB1kuwL
A44: 43 | B44: TikTok | C44: Komen | D44: 2024-09-29 | E44: Sakit belakang / badan | F44: Boleh doctor suggest tilam yang sesuai utk warga emas yang ada sakit tulang belakang? Saya nak carikan untuk ibu saya | G44: https://www.tiktok.com/@drzahir.ortho/video/7359054445277203730
A45: 44 | B45: TikTok | C45: Komen | D45: 2025-06-21 | E45: Sakit belakang / badan | F45: tp bila tido atas tilam ni rasa sakit pulak badan.. | G45: https://www.tiktok.com/@salam_coway/video/7516809339831684370 | H45: Ya
A46: 45 | B46: TikTok | C46: Komen | D46: 2025-12-29 | E46: Sakit belakang / badan | F46: tilam sy skrg punca sy sakit badan, boleh sy tahu suggestion mana yg ssuai? sbb tgh cari tilam, xdaya dh nk tahan badan n sakit blkg | G46: https://www.tiktok.com/@salam_coway/video/7516809339831684370 | H46: Ya
A47: 46 | B47: TikTok | C47: Komen | D47: 2026-03-11 | E47: Sakit belakang / badan | F47: Sy dari Kota Kinabalu mencari tilam warga emas, ibu sy sakit blkg dan pinggang mohon bagi info | G47: https://www.tiktok.com/@drzahir.ortho/video/7359054445277203730
A48: 47 | B48: TikTok | C48: Komen | D48: 2026-04-26 | E48: Sakit belakang / badan | F48: macam tau tau je tgh cari tilam baru, yg lama dh nipis sakit blkg 😭 | G48: https://www.tiktok.com/@fiqahar/video/7632990429172092181
A49: 48 | B49: TikTok | C49: Komen | D49: 2026-07-14 | E49: Sakit belakang / badan | F49: sy pagi2 sakit pinggan.. doctor sarankan pakai tilam latex.. cari yg original.. waranty brp tahun tilam ni | G49: https://www.tiktok.com/@ajmal_legacy/video/7647945200601468168
A50: 49 | B50: TikTok | C50: Komen | D50: 2026-08-01 | E50: Sakit belakang / badan | F50: side sleeper dan selalu rasa lenguh badan selepas bangun tidur | G50: https://www.tiktok.com/@vonomalaysia/video/7527122276873981185
A51: 50 | B51: TikTok | C51: Komen | D51: 2026-08-25 | E51: Sakit belakang / badan | F51: abang blh x review tilam lipat pulak penat dh cri yg okay semua sakit badan😌 | G51: https://www.tiktok.com/@te4hhh._/video/7677509010823646485
A52: 51 | B52: Lowyat | C52: Post forum | D52: 2020-01-30 | E52: Sakit belakang / badan | F52: we just got the serta mattress and it was fine until my wife wake up recently and felt painful at the back. | G52: https://forum.lowyat.net/topic/843907/+6260
A53: 52 | B53: Lowyat | C53: Post forum | D53: 2020-02-01 | E53: Sakit belakang / badan | F53: After less than 1 month, i started having back issues. | G53: https://forum.lowyat.net/topic/843907/+6260
A54: 53 | B54: Lowyat | C54: Post forum | D54: 2020-09-15 | E54: Sakit belakang / badan | F54: Im a big guy, 330lbs, 5'11, constant back pain from an old injury, need a new mattress ASAP. | G54: https://forum.lowyat.net/topic/843907/+6520
A55: 54 | B55: Lowyat | C55: Post forum | D55: 2023-07-19 | E55: Sakit belakang / badan | F55: i usually have back pain, so want to try something that gives proper support | G55: https://forum.lowyat.net/topic/843907/+7487
A56: 55 | B56: Lowyat | C56: Post forum | D56: 2023-07-22 | E56: Sakit belakang / badan | F56: Ageing already and don't want to have backpain. | G56: https://forum.lowyat.net/topic/843907/+7487
A57: 56 | B57: Lowyat | C57: Post forum | D57: 2025-11-03 | E57: Sakit belakang / badan | F57: Hi can suggest me good mattress that best support my lumbar back problem? | G57: https://forum.lowyat.net/topic/843907/+8000
A58: 57 | B58: Threads | C58: Post | D58: 2025-07-15 | E58: Maklumat produk kurang / keliru memilih | F58: Boleh tak share tilam yang bagus tak tengelam bila tidur? Brand apa dan harga berapa perlu kita invest untuk beli tilam? | G58: https://www.threads.com/@razip_zainijasri/post/DMHPrSKRgVd
... A76: 75 | B76: Threads | C76: Post | D76: 2026-10-02 | E76: Mendap / lekuk | F76: Anyone ada masalah sinking bed? Tilam tenggelam, sbb terlalu lma tido kat one spot? Do you guys have any solution? Sakit belakang teruk ni setiap malam | G76: https://www.threads.com/@leoinhis24/post/Dd_ty6WE1C2
A77: 76 | B77: TikTok | C77: Komen | D77: 2024-10-06 | E77: Mendap / lekuk | F77: tilam ni akan tenggelam x lama2. berapa keberatan max | G77: https://www.tiktok.com/@amirul_coway_/video/7408816814542687505 | H77: Ya
A78: 77 | B78: TikTok | C78: Komen | D78: 2026-05-14 | E78: Mendap / lekuk | F78: sy tilam span biasa tu lau baring lma2 mendap esknya bgn sakit belakang🥺 | G78: https://www.tiktok.com/@fiqahar/video/7632990429172092181
A79: 78 | B79: TikTok | C79: Komen | D79: 2026-06-30 | E79: Mendap / lekuk | F79: nmpak lembut..lma2 tak tenggelam ker bahagian tidur tu | G79: https://www.tiktok.com/@ajmal_legacy/video/7647945200601468168
A80: 79 | B80: TikTok | C80: Komen | D80: 2026-07-01 | E80: Mendap / lekuk | F80: melendut x klu dh lama2 sy baru je tukar tilam bulan 2, tp xlama lepastu jd melendut,sakit belakang datang balik | G80: https://www.tiktok.com/@jielaracuntiktok/video/7655255475436424455
A81: 80 | B81: TikTok | C81: Komen | D81: 2026-08-05 | E81: Mendap / lekuk | F81: kalau obese lama² lendut tak | G81: https://www.tiktok.com/@nasuharazali05/video/7643081281894419720
A82: 81 | B82: TikTok | C82: Komen | D82: 2026-08-23 | E82: Mendap / lekuk | F82: Tengelam habis dia punya spring.. berbaloi dengan harga.. pakai setahun dua ok lah tu | G82: https://www.tiktok.com/@hairulvcool/video/7661054206257745170
A83: 82 | B83: Lowyat | C83: Post forum | D83: 2017-06-18 | E83: Mendap / lekuk | F83: I'm using a Dunlopillo Duchess for 8 years now no problem so far but maybe it is due to wear and tear, it is sinking about 30-40% already.... | G83: https://forum.lowyat.net/topic/843907/+4920
A84: 83 | B84: Lowyat | C84: Post forum | D84: 2020-09-18 | E84: Mendap / lekuk | F84: I read review that it becomes saggy after 3-5 years and Serta wont honor its warranty bacoz of that. | G84: https://forum.lowyat.net/topic/843907/+6520
A85: 84 | B85: Lowyat | C85: Post forum | D85: 2021-12-29 | E85: Mendap / lekuk | F85: How do they feel after 6 months / 1year of usage? Still firm or dented already? | G85: https://forum.lowyat.net/topic/843907/+6960
A86: 85 | B86: Threads | C86: Post | D86: 2026-01-13 | E86: Kotor / kebersihan | F86: anak saiya terkencing atas tilam while potty train, dah basuh tilam jadi begini pula . Dah pakai alas waterproof tapi mana silapnya, tetap bocor juga. | G86: https://www.threads.com/@ommiraiyan/post/DTblhclk9Cm
A87: 86 | B87: Threads | C87: Balasan | D87: 2026-08-15 | E87: Kotor / kebersihan | F87: tak lama lagi tu naik lah kuning2 dekat tilam tu😅 | G87: https://www.threads.com/@aizawahab/post/DcBtUSglP_H | H87: Ya
A88: 87 | B88: Threads | C88: Post | D88: 2026-09-21 | E88: Kotor / kebersihan | F88: Kalau anak terkencing atas tilam, korang biasanya cuci macam mana? | G88: https://www.threads.com/@iamabangjai/post/DdiLbPomV04
A89: 88 | B89: Threads | C89: Post | D89: 2026-09-24 | E89: Kotor / kebersihan | F89: Mencari orang yg buat service cuci tilam. Tilam yg lipat tu je sbb anak kencing atas tu. | G89: https://www.threads.com/@qilahnis/post/Ddpr9igGOFj
A90: 89 | B90: TikTok | C90: Komen | D90: 2023-11-26 | E90: Kotor / kebersihan | F90: kt rumah rawang toe bilik sy Guna tilam coway tp mse sy blk toe sy terkejut tilam coway dh terkulat padahal baru lgi beli... | G90: https://www.tiktok.com/@amirul_coway_/video/7283047892829457665 | H90: Ya
A91: 90 | B91: TikTok | C91: Komen | D91: 2024-11-30 | E91: Kotor / kebersihan | F91: buatlh warna gelap. kna kotor sikit nmpk sgt | G91: https://www.tiktok.com/@sultera.official/video/7427039598104136967
A92: 91 | B92: TikTok | C92: Komen | D92: 2025-03-20 | E92: Kotor / kebersihan | F92: yg lite tu kalau ank terkencing mcm mana nk cuci ye | G92: https://www.tiktok.com/@amirul_coway_/video/7442192131587886354 | H92: Ya
A93: 92 | B93: TikTok | C93: Komen | D93: 2025-04-07 | E93: Kotor / kebersihan | F93: waterproof ke? sesuai tak utk kanak2 kencing mlm? | G93: https://www.tiktok.com/@sultera.official/video/7427039598104136967
A94: 93 | B94: TikTok | C94: Komen | D94: 2026-06-27 | E94: Kotor / kebersihan | F94: tengah tidur tetiba gatal kat kaki.. tergaru garu aku dibuatnya.. tilam baru.. | G94: https://www.tiktok.com/@red.kleenz/video/7655932419291352341
A95: 94 | B95: TikTok | C95: Komen | D95: 2026-06-29 | E95: Kotor / kebersihan | F95: apalah tilam mahal mahal tak ada anti bedbug!! | G95: https://www.tiktok.com/@red.kleenz/video/7655932419291352341
A96: 95 | B96: Lowyat | C96: Post forum | D96: 2021-12-28 | E96: Kotor / kebersihan | F96: i only sit on the display bed so far (i afraid too many ppl lay down have virus on bed) | G96: https://forum.lowyat.net/topic/843907/+6960
A97: 96 | B97: Lowyat | C97: Post forum | D97: 2023-07-08 | E97: Kotor / kebersihan | F97: my mattress kena purple (grape favour) yakult. and now the portion is purple. anyway i can remove this stain? | G97: https://forum.lowyat.net/topic/843907/+7487
A98: 97 | B98: Threads | C98: Balasan | D98: 2025-09-07 | E98: Jurujual / harga tak telus | F98: Agent prnah wsap husband push amek tilam coway..bila tny brapa per bulan, brapa tahun. Hmm dah block je num agent tu 😅 | G98: https://www.threads.com/@rafidahsamat/post/DORE_lRk0J0 | H98: Ya
A99: 98 | B99: TikTok | C99: Komen | D99: 2024-10-14 | E99: Jurujual / harga tak telus | F99: If an ad says it won't tear your pocket, at the same time they wont display the prices, then you should already know its a scam | G99: https://www.tiktok.com/@reshlikespie/video/7393974696586251536
A100: 99 | B100: TikTok | C100: Komen | D100: 2024-12-04 | E100: Jurujual / harga tak telus | F100: Set tilam dan katil serta aircond berapa bulanan? Bayaran ansuran berapa lama? | G100: https://www.tiktok.com/@amirul_coway_/video/7408816814542687505 | H100: Ya
A101: 100 | B101: TikTok | C101: Komen | D101: 2025-03-26 | E101: Jurujual / harga tak telus | F101: Bulanan queen rm109 mmg dpt betul2 mcm dlm video nie ke? | G101: https://www.tiktok.com/@amirul_coway_/video/7408816814542687505 | H101: Ya
A102: 101 | B102: TikTok | C102: Komen | D102: 2025-07-09 | E102: Jurujual / harga tak telus | F102: sbb 10mlm td ad org wsp akk pasal topper sampai sini ak cari . sbb ingtkn scam haha. | G102: https://www.tiktok.com/@_syaifulaiman/video/7490791598377291026 | H102: Ya
A103: 102 | B103: TikTok | C103: Komen | D103: 2026-06-28 | E103: Jurujual / harga tak telus | F103: patutlah setiap hari dorg call sy offer mcm2... tutup ac lama tambah hutang baru nasib x terpengaruh 😂😂 | G103: https://www.tiktok.com/@red.kleenz/video/7655932419291352341 | H103: Ya
A104: 103 | B104: Lowyat | C104: Post forum | D104: 2017-06-21 | E104: Jurujual / harga tak telus | F104: If they tell you prices are controlled and so on, go to another re-seller. | G104: https://forum.lowyat.net/topic/843907/+4920
A105: 104 | B105: Lowyat | C105: Post forum | D105: 2020-02-01 | E105: Jurujual / harga tak telus | F105: Right after marriage, I was pressured into making a decision quick | G105: https://forum.lowyat.net/topic/843907/+6260
A106: 105 | B106: Lowyat | C106: Post forum | D106: 2020-02-01 | E106: Jurujual / harga tak telus | F106: A quick shop around reveal the price is actually RM1.2k (the initial shop try to chop chop me). | G106: https://forum.lowyat.net/topic/843907/+6260
A107: 106 | B107: Lowyat | C107: Post forum | D107: 2020-09-06 | E107: Jurujual / harga tak telus | F107: This get me wonder who should I trust and rather disappointing if it assembles locally without maintaining the quality to achieve better margin. | G107: https://forum.lowyat.net/topic/843907/+6520
A108: 107 | B108: Lowyat | C108: Post forum | D108: 2021-12-15 | E108: Jurujual / harga tak telus | F108: I heard they are own oem rebrand. Not sure if I wanna spend on it or just get established brand. | G108: https://forum.lowyat.net/topic/843907/+6960
A109: 108 | B109: Lowyat | C109: Post forum | D109: 2025-10-30 | E109: Jurujual / harga tak telus | F109: recently saw an ad for dunlopillo warehouse sale happening now, worth it to pay them a visit, or better to just buy from a proper boutique? | G109: https://forum.lowyat.net/topic/843907/+8000
A110: 109 | B110: Threads | C110: Balasan | D110: 2025-09-04 | E110: Kontrak / bayaran bulanan / servis | F110: Jangan sis mahal kalau u kira balik | G110: https://www.threads.com/@vicky.littlewolf/post/DOK0cDFAXFT | H110: Ya
A111: 110 | B111: Threads | C111: Post | D111: 2025-09-06 | E111: Kontrak / bayaran bulanan / servis | F111: Aku baru sign up tilam queen saiz daripada coway. Bulanan RM 49 kontrak 7 tahun. Berbaloi ke tak? Taknak agent coway yang respond ye haha | G111: https://www.threads.com/@tuanlxkmxn/post/DOQO10bEf8y | H111: Ya
A112: 111 | B112: Threads | C112: Balasan | D112: 2025-09-07 | E112: Kontrak / bayaran bulanan / servis | F112: 49x12x7=4,116 gila | G112: https://www.threads.com/@tahribat_uzay/post/DOSoe7EkVGs | H112: Ya
A113: 112 | B113: Threads | C113: Balasan | D113: 2025-09-08 | E113: Kontrak / bayaran bulanan / servis | F113: X berbaloi utk amik monthly installment. Kalau u kira amik bayar lum sum lagi banyak jimat. Jgn terpedaya. | G113: https://www.threads.com/@ysmnikhsan/post/DOUq1dKkmPz | H113: Ya
A114: 113 | B114: Threads | C114: Balasan | D114: 2025-09-08 | E114: Kontrak / bayaran bulanan / servis | F114: Mudah kena makan sampai tilam pon loan 😂 | G114: https://www.threads.com/@ezuee_/post/DOTw6g_Enl2 | H114: Ya
A115: 114 | B115: Threads | C115: Balasan | D115: 2025-09-08 | E115: Kontrak / bayaran bulanan / servis | F115: Awal² kami ok je tp bila da lama kami rasa segan plak nk bgi org msuk pi servce tilam kita yg berpeta😅 | G115: https://www.threads.com/@_jemahsyantik_/post/DOUF-BriuLn | H115: Ya
A116: 115 | B116: Threads | C116: Balasan | D116: 2026-09-07 | E116: Kontrak / bayaran bulanan / servis | F116: Tak nak hutang dah😭😭😭. Nak beli cash tak mmpu pulak😄. | G116: https://www.threads.com/@me_kinna/post/Dc98vqAkgJy | H116: Ya
A117: 116 | B117: TikTok | C117: Komen | D117: 2025-10-21 | E117: Kontrak / bayaran bulanan / servis | F117: Berbaloi ke x byr 7 tahun?? Sy br cdang nk beli, tp nk tgk review jujur korang dlu | G117: https://www.tiktok.com/@salam_coway/video/7516809339831684370 | H117: Ya
A118: 117 | B118: TikTok | C118: Komen | D118: 2026-05-28 | E118: Kontrak / bayaran bulanan / servis | F118: sebelum 3 tahun badan dah sakit2 sbb topper dah nipis....x selesa nk tidur...kene tggu bulan 9 cukup 3 tahun baru boleh tukar...badan dah lunyai...hurmm bulan2 tetap kene bayar not value for money 💰 | G118: https://www.tiktok.com/@_syaifulaiman/video/7490791598377291026 | H118: Ya
A119: 118 | B119: TikTok | C119: Komen | D119: 2026-06-28 | E119: Kontrak / bayaran bulanan / servis | F119: I pon tak suka beli produk byrn bulanan yg jika total mahal nak mampus. | G119: https://www.tiktok.com/@red.kleenz/video/7655932419291352341 | H119: Ya
A120: 119 | B120: TikTok | C120: Komen | D120: 2026-06-29 | E120: Kontrak / bayaran bulanan / servis | F120: Semasa masih ada kontrak coway, coway buat tak tahu je kee? | G120: https://www.tiktok.com/@red.kleenz/video/7655932419291352341 | H120: Ya
...

Sheet Nota
A1: Perkara | B1: Nota
A2: Kaedah | B2: Ayat diambil verbatim daripada kandungan awam. Satu baris = satu ayat pain. Tiada kolum nama pengguna; link sumber ialah link awam post/video untuk semakan.
A3: Threads | B3: ~15 carian (cth. 'tilam sakit belakang', 'tilam tenggelam', 'tilam coway', 'tilam keras sangat') + balasan pada 8 post yang ramai komen. Post yang jelas promosi/affiliate tidak dimasukkan.
A4: TikTok | B4: 81 video daripada 4 carian (tilam sakit belakang, tilam tenggelam, tilam coway, review tilam jujur). 2,089 komen ditarik, ditapis kepada BM/Inggeris dan kata kunci pain, kemudian dipilih manual. Link menghala ke video (komen individu tiada link sendiri). Komen 'nak link' dan pujian ejen/affiliate dibuang.
A5: Lowyat | B5: 10 halaman thread 'Household Mattress, which brand to go for?' (2017–2025).
A6: Reddit | B6: Tidak termasuk; disekat daripada sesi ini.
A7: Kategori | B7: Dilabel manual oleh Claude, satu ayat satu kategori. Tukar di kolum E tab 'Ayat Pain' dan Ringkasan akan ikut.
A8: Sebut Coway | B8: 'Ya' jika ayat itu menyebut Coway atau datang daripada video/thread yang khusus tentang tilam Coway. Baris diwarnakan kuning muda.
A9: Bias | B9: Carian TikTok dan Threads condong kepada pembeli yang sedang survey (ramai bertanya, kurang yang dah beli). Video jenama/ejen menarik komen positif, jadi pain di situ mungkin terkurang kira.
